[
    {
        "题号": "P1334",
        "题目": "瑞瑞的木板",
        "标签": [
            "堆",
            "福建省历届夏令营",
            "排序"
        ],
        "难度": "普及/提高−"
    },
    {
        "题号": "P1335",
        "题目": "[NOI2013] 小Q的修炼",
        "标签": [
            "模拟",
            "字符串",
            "2013",
            "NOI",
            "提交答案",
            "Special Judge",
            "枚举"
        ],
        "难度": "NOI/NOI+/CTSC"
    },
    {
        "题号": "P1336",
        "题目": "最佳课题选择",
        "标签": [
            "动态规划,dp",
            "福建省历届夏令营"
        ],
        "难度": "普及/提高−"
    }
]